pydantic_cereal/__init__.py
pydantic_cereal/_metadata.py
pydantic_cereal/_path_utils.py
pydantic_cereal/_protocols.py
pydantic_cereal/_utils.py
pydantic_cereal/errors.py
pydantic_cereal/main.py
pydantic_cereal/py.typed
pydantic_cereal/version.py
pydantic_cereal/examples/__init__.py
pydantic_cereal/examples/ex_pd.py
pydantic_cereal/examples/ex_pl.py
pydantic_cereal-0.0.6.dist-info/LICENSE
pydantic_cereal-0.0.6.dist-info/METADATA
pydantic_cereal-0.0.6.dist-info/WHEEL
pydantic_cereal-0.0.6.dist-info/top_level.txt
pydantic_cereal-0.0.6.dist-info/RECORD
