Metadata-Version: 2.1
Name: pydantic-cereal
Version: 0.0.6
Summary: Advanced serialization for Pydantic models
License: MIT License
Keywords: pydantic,serialize,fsspec,yaml
Classifier: Programming Language :: Python :: 3
Classifier: Development Status :: 2 - Pre-Alpha
Classifier: Intended Audience :: Developers
Classifier: License :: OSI Approved :: MIT License
Classifier: Topic :: Software Development
Classifier: Typing :: Typed
Requires-Python: >=3.9
License-File: LICENSE
Requires-Dist: pydantic <3,>=2
Requires-Dist: fsspec
Requires-Dist: universal-pathlib
Provides-Extra: datatests
Requires-Dist: pandas ~=2.1.3 ; extra == 'datatests'
Requires-Dist: pyarrow ~=14.0.1 ; extra == 'datatests'
Requires-Dist: pyspark ~=3.5.0 ; extra == 'datatests'
Requires-Dist: polars ~=0.20.7 ; extra == 'datatests'
Provides-Extra: dev
Requires-Dist: setuptools >=61.0.0 ; extra == 'dev'
Requires-Dist: setuptools-scm[toml] >=6.2 ; extra == 'dev'
Requires-Dist: wheel >=0.41 ; extra == 'dev'
Requires-Dist: pre-commit ==3.6.0 ; extra == 'dev'
Requires-Dist: ruff ==0.2.1 ; extra == 'dev'
Requires-Dist: black ==23.12.1 ; extra == 'dev'
Requires-Dist: isort ==5.13.2 ; extra == 'dev'
Requires-Dist: mypy ==1.8.0 ; extra == 'dev'
Requires-Dist: pytest ==7.4.4 ; extra == 'dev'
Requires-Dist: pytest-lazy-fixture ==0.6.3 ; extra == 'dev'
Requires-Dist: pytest-cases ==3.8.2 ; extra == 'dev'
Requires-Dist: jupyter ; extra == 'dev'
Requires-Dist: ipykernel ; extra == 'dev'
Requires-Dist: pandas-stubs ; extra == 'dev'
Requires-Dist: polars ; extra == 'dev'
Requires-Dist: gcsfs ~=2023.12.2 ; extra == 'dev'
Provides-Extra: docs
Requires-Dist: mkdocs ==1.5.3 ; extra == 'docs'
Requires-Dist: mkdocs-material ==9.5.9 ; extra == 'docs'
Requires-Dist: mkdocstrings ==0.24.0 ; extra == 'docs'
Requires-Dist: mkdocstrings-python ==1.8.0 ; extra == 'docs'
Requires-Dist: mkdocs-jupyter ==0.24.6 ; extra == 'docs'
Requires-Dist: pygments ==2.17.2 ; extra == 'docs'
